MANIFEST.in
README.rst
setup.py
xbotium/__init__.py
xbotium.egg-info/PKG-INFO
xbotium.egg-info/SOURCES.txt
xbotium.egg-info/dependency_links.txt
xbotium.egg-info/not-zip-safe
xbotium.egg-info/requires.txt
xbotium.egg-info/top_level.txt