Metadata-Version: 1.1
Name: xbotium
Version: 0.1
Summary: this is a prototype
Home-page: http://github.com/botium/xbotium
Author: Sentino
Author-email: hi@sentino.org
License: MIT
Platform: UNKNOWN
Classifier: License :: OSI Approved :: MIT License
Classifier: Programming Language :: Python :: 3.5
Classifier: Topic :: Text Processing :: Linguistic
